example_package_HA_TUONG_NGUYEN/__init__.py
example_package_HA_TUONG_NGUYEN/example.py
example_package_HA_TUONG_NGUYEN-0.0.0.dist-info/LICENSE
example_package_HA_TUONG_NGUYEN-0.0.0.dist-info/METADATA
example_package_HA_TUONG_NGUYEN-0.0.0.dist-info/WHEEL
example_package_HA_TUONG_NGUYEN-0.0.0.dist-info/top_level.txt
example_package_HA_TUONG_NGUYEN-0.0.0.dist-info/RECORD
