Metadata-Version: 2.1
Name: example_package_HA_TUONG_NGUYEN
Version: 0.0.0
Summary: A small example package
Author-email: Tuong Nguyen Ha <hatuongnguyen@gmail.com>
Maintainer-email: Tuong Nguyen Ha <hatuongnguyen@gmail.com>
License: # https://choosealicense.com/
Project-URL: Homepage, https://github.com/hatuongnguyen/sampleproject
Keywords: SetupPythonPackageIndex,Test,MyTest,Tuong Nguyen Ha,Template
Classifier: Programming Language :: Python :: 3
Classifier: License :: OSI Approved :: MIT License
Classifier: Operating System :: OS Independent
Requires-Python: >=3.8
License-File: LICENSE
Requires-Dist: numpy
Requires-Dist: matplotlib
Requires-Dist: pandas
